fastrapi-0.1.6.dist-info/METADATA
fastrapi-0.1.6.dist-info/WHEEL
fastrapi-0.1.6.dist-info/licenses/LICENSE
fastrapi/__init__.py
fastrapi/fastrapi.cpython-312-aarch64-linux-gnu.so
fastrapi-0.1.6.dist-info/RECORD
