Metadata-Version: 2.4
Name: fastrapi
Version: 0.1.6
Classifier: Programming Language :: Rust
Classifier: Programming Language :: Python :: Implementation :: CPython
Classifier: Programming Language :: Python :: Implementation :: PyPy
Classifier: License :: OSI Approved :: MIT License
Classifier: Topic :: Internet :: WWW/HTTP :: HTTP Servers
Classifier: Topic :: Software Development :: Libraries :: Application Frameworks
Requires-Dist: pydantic>=2.10.6
License-File: LICENSE
Summary: A high-performance Python API framework powered by Rust
Keywords: fastapi,fastrapi,api,web,framework,fast,rust
Author-email: Preetham <ppmpreetham1@gmail.com>
Requires-Python: >=3.8
Project-URL: homepage, https://github.com/ppmpreetham/fastrapi
Project-URL: documentation, https://github.com/ppmpreetham/fastrapi#readme
Project-URL: repository, https://github.com/ppmpreetham/fastrapi.git
Project-URL: bug tracker, https://github.com/ppmpreetham/fastrapi/issues
